{
  "version": "0.1.1",
  "description": "Account Abstraction Snap written in TypeScript.",
  "proposedName": "AA Snap",
  "repository": {
    "type": "git",
    "url": "https://github.com/therealharpaljadeja/aa-snap"
  },
  "source": {
    "shasum": "kQIlvxLENMZ8jeGA/qc99uU8pNOgUuDhNyHesJBEIuk=",
    "location": {
      "npm": {
        "filePath": "dist/bundle.js",
        "iconPath": "images/icon.svg",
        "packageName": "4337-snap",
        "registry": "https://registry.npmjs.org/"
      }
    }
  },
  "initialPermissions": {
    "snap_manageAccounts": {},
    "snap_manageState": {},
    "snap_notify": {},
    "endowment:network-access": {},
    "snap_dialog": {},
    "endowment:ethereum-provider": {},
    "endowment:rpc": {
      "dapps": true,
      "snaps": false
    }
  },
  "manifestVersion": "0.1"
}
